chunter/__init__.py
chunter/chunter.py
chunter/data_utils.py
chunter-0.2.0.dist-info/METADATA
chunter-0.2.0.dist-info/WHEEL
chunter-0.2.0.dist-info/licenses/LICENSE
chunter-0.2.0.dist-info/RECORD
