Metadata-Version: 2.4
Name: chunter
Version: 0.2.0
Summary: Cohomological analysis of circular structures in scRNA-seq data
Author-email: Smelly Maggs <maggs@mpi-cbg.de>
License-File: LICENSE
Requires-Python: >=3.10
Requires-Dist: gseapy>=1.1.8
Requires-Dist: leidenalg>=0.10.2
Requires-Dist: magic-impute>=3.0.0
Requires-Dist: nbformat>=5.10.4
Requires-Dist: numpy>=2.2.5
Requires-Dist: pandas>=2.2.3
Requires-Dist: plotly>=6.0.1
Requires-Dist: python-igraph>=0.11.8
Requires-Dist: ringity>=0.4a2
Requires-Dist: ripser>=0.6.12
Requires-Dist: scanpy>=1.11.1
